DockerENT/__init__.py
DockerENT/__main__.py
DockerENT/config_parser.py
DockerENT/controller.py
DockerENT/output_worker.py
DockerENT/scanner_workers.py
DockerENT/web_app.py
DockerENT/docker_nw_plugins/__init__.py
DockerENT/docker_nw_plugins/docker_nw_sample_plugin.py
DockerENT/docker_plugins/__init__.py
DockerENT/docker_plugins/docker_cmd_history_info.py
DockerENT/docker_plugins/docker_file_info.py
DockerENT/docker_plugins/docker_filesystem_info.py
DockerENT/docker_plugins/docker_network_info.py
DockerENT/docker_plugins/docker_plaintext_password_info.py
DockerENT/docker_plugins/docker_process_info.py
DockerENT/docker_plugins/docker_sample_plugin.py
DockerENT/docker_plugins/docker_security_profiles_info.py
DockerENT/docker_plugins/docker_system_info.py
DockerENT/docker_plugins/docker_user_info.py
DockerENT/docker_plugins/docker_writeable_cronjobs_info.py
DockerENT/output_plugins/__init__.py
DockerENT/output_plugins/file.py
DockerENT/output_plugins/html.py
DockerENT/utils/__init__.py
DockerENT/utils/utils.py
DockerENT-0.1.15.dist-info/LICENSE
DockerENT-0.1.15.dist-info/METADATA
DockerENT-0.1.15.dist-info/WHEEL
DockerENT-0.1.15.dist-info/entry_points.txt
DockerENT-0.1.15.dist-info/top_level.txt
DockerENT-0.1.15.dist-info/RECORD
