Metadata-Version: 2.1
Name: DockerENT
Version: 0.1.15
Summary: A tool to analyse issues with running docker container(s)
Home-page: https://github.com/r0hi7/DockerENT
License: UNKNOWN
Keywords: docker runtime scanning framework
Platform: UNKNOWN
Classifier: Programming Language :: Python :: 3
Classifier: License :: OSI Approved :: MIT License
Classifier: Operating System :: OS Independent
Requires-Python: >=3.7
Requires-Dist: streamlit
Requires-Dist: certifi (==2020.6.20)
Requires-Dist: chardet (==3.0.4)
Requires-Dist: colorama (==0.4.3)
Requires-Dist: commonmark (==0.9.1)
Requires-Dist: docker (==4.2.1)
Requires-Dist: idna (==2.9)
Requires-Dist: Jinja2 (==2.11.2)
Requires-Dist: MarkupSafe (==1.1.1)
Requires-Dist: mccabe (==0.6.1)
Requires-Dist: pprintpp (==0.4.0)
Requires-Dist: pycodestyle (==2.6.0)
Requires-Dist: pydocstyle (==5.0.2)
Requires-Dist: pyflakes (==2.2.0)
Requires-Dist: Pygments (==2.6.1)
Requires-Dist: pylama (==7.7.1)
Requires-Dist: PyYAML (==5.3.1)
Requires-Dist: requests (==2.24.0)
Requires-Dist: rich (==2.2.6)
Requires-Dist: six (==1.15.0)
Requires-Dist: snowballstemmer (==2.0.0)
Requires-Dist: typing-extensions (==3.7.4.2)
Requires-Dist: urllib3 (==1.25.9)
Requires-Dist: websocket-client (==0.57.0)
Requires-Dist: DockerENT
